Metadata-Version: 2.4
Name: il-supermarket-parser
Version: 0.2.2
Summary: python package that process the data dumped by the israeli supermarket
Home-page: https://github.com/OpenIsraeliSupermarkets/israeli-supermarket-parsers
Author: Sefi Erlich
Author-email: erlichsefi@gmail.com
License: MIT
Keywords: israel,israeli,scraper,supermarket
Classifier: Development Status :: 3 - Alpha
Classifier: Intended Audience :: Developers
Classifier: Topic :: Software Development :: Build Tools
Classifier: License :: OSI Approved :: MIT License
Classifier: Programming Language :: Python :: 3
Classifier: Programming Language :: Python :: 3.4
Classifier: Programming Language :: Python :: 3.5
Classifier: Programming Language :: Python :: 3.6
License-File: LICENSE.txt
Requires-Dist: pandas==2.2.2
Requires-Dist: lxml==5.2.1
Requires-Dist: pymongo==4.6.3
Requires-Dist: il-supermarket-scraper>=0.6.1
Requires-Dist: tqdm>=4.66
Requires-Dist: dnspython>=2.6.1
Provides-Extra: test
Requires-Dist: pytest; extra == "test"
Requires-Dist: pytest-xdist; extra == "test"
Dynamic: author
Dynamic: author-email
Dynamic: classifier
Dynamic: description
Dynamic: description-content-type
Dynamic: home-page
Dynamic: keywords
Dynamic: license
Dynamic: license-file
Dynamic: provides-extra
Dynamic: requires-dist
Dynamic: summary
